Metadata-Version: 2.3
Name: mkdocs-include-files
Version: 0.1.0
Summary: 
Author: Caleb Perkinson
Author-email: CalebPerkinson@gmail.com
Requires-Python: >=3.12
Classifier: Programming Language :: Python :: 3
Classifier: Programming Language :: Python :: 3.12
Classifier: Programming Language :: Python :: 3.13
Requires-Dist: mkdocs (>=1.5.0,<2.0.0)
